terraform_named_cloudflare/__init__.py
terraform_named_cloudflare/__main__.py
terraform_named_cloudflare/templates/A.tf.j2
terraform_named_cloudflare/templates/AAAA.tf.j2
terraform_named_cloudflare/templates/CNAME.tf.j2
terraform_named_cloudflare/templates/MX.tf.j2
terraform_named_cloudflare/templates/SRV.tf.j2
terraform_named_cloudflare/templates/TXT.tf.j2
terraform_named_cloudflare/templates/variables.tf.j2
terraform_named_cloudflare-0.0.2.data/scripts/terraform-named-cloudflare
terraform_named_cloudflare-0.0.2.dist-info/LICENSE
terraform_named_cloudflare-0.0.2.dist-info/METADATA
terraform_named_cloudflare-0.0.2.dist-info/WHEEL
terraform_named_cloudflare-0.0.2.dist-info/top_level.txt
terraform_named_cloudflare-0.0.2.dist-info/RECORD
