Metadata-Version: 2.1
Name: terraform-named-cloudflare
Version: 0.0.2
Summary: Module to easily convert Bind9 (named) zones into Terraform CloudFlare provider records definitions
Home-page: https://github.com/pa-yourserveradmin-com/terraform-named-cloudflare
Author: Andrew Poltavchenko
Author-email: pa@yourserveradmin.com
License: MIT
Platform: UNKNOWN
Classifier: Development Status :: 1 - Planning
Classifier: License :: OSI Approved :: MIT License
Classifier: Natural Language :: English
Classifier: Operating System :: OS Independent
Classifier: Programming Language :: Python :: 3 :: Only
Classifier: Programming Language :: Python :: Implementation :: CPython
Requires-Dist: Jinja2 (==2.11.1)
Requires-Dist: MarkupSafe (==1.1.1)
